pytest_rerun/__init__.py
pytest_rerun/conftest.py
pytest_rerun/pytest_rerun.py
pytest_rerun-0.0.1.dist-info/LICENSE
pytest_rerun-0.0.1.dist-info/METADATA
pytest_rerun-0.0.1.dist-info/WHEEL
pytest_rerun-0.0.1.dist-info/entry_points.txt
pytest_rerun-0.0.1.dist-info/top_level.txt
pytest_rerun-0.0.1.dist-info/RECORD
