Metadata-Version: 1.0
Name: pytest-rerun
Version: 0.0.1
Summary: Re-run only changed files in specified branch
Home-page: http://github.com/zeburek/pytest-rerun/
Author: Parviz Khavari
Author-email: me@parviz.pw
License: UNKNOWN
Platform: UNKNOWN
